odoo/addons/l10n_ro_account/README.rst
odoo/addons/l10n_ro_account/__init__.py
odoo/addons/l10n_ro_account/__manifest__.py
odoo/addons/l10n_ro_account/i18n/l10n_ro_account.pot
odoo/addons/l10n_ro_account/i18n/ro.po
odoo/addons/l10n_ro_account/models/__init__.py
odoo/addons/l10n_ro_account/models/account_account.py
odoo/addons/l10n_ro_account/models/account_payment.py
odoo/addons/l10n_ro_account/readme/CONTRIBUTORS.rst
odoo/addons/l10n_ro_account/readme/DESCRIPTION.rst
odoo/addons/l10n_ro_account/static/description/icon.png
odoo/addons/l10n_ro_account/static/description/index.html
odoo/addons/l10n_ro_account/tests/__init__.py
odoo/addons/l10n_ro_account/tests/test_account.py
odoo/addons/l10n_ro_account/tests/test_payment.py
odoo14_addon_l10n_ro_account-14.0.1.3.0.dist-info/METADATA
odoo14_addon_l10n_ro_account-14.0.1.3.0.dist-info/WHEEL
odoo14_addon_l10n_ro_account-14.0.1.3.0.dist-info/top_level.txt
odoo14_addon_l10n_ro_account-14.0.1.3.0.dist-info/RECORD
